<annotation>
        <folder>FOLDER</folder>
        <filename>045329741.jpg</filename>
        <path>data/scenes/val\045329741.jpg</path>
        <source>
                <database>Unknown</database>
        </source>
        <size>
                <width>720</width>
                <height>720</height>
                <depth>3</depth>
        </size>
 <object>
                <name>3s</name>
                <pose>Unspecified</pose>
                <truncated>0</truncated>
                <difficult>0</difficult>
                <bndbox>
                        <xmin>253</xmin>
                        <ymin>340</ymin>
                        <xmax>291</xmax>
                        <ymax>390</ymax>
                </bndbox>
        </object>
 <object>
                <name>Jh</name>
                <pose>Unspecified</pose>
                <truncated>0</truncated>
                <difficult>0</difficult>
                <bndbox>
                        <xmin>287</xmin>
                        <ymin>330</ymin>
                        <xmax>321</xmax>
                        <ymax>382</ymax>
                </bndbox>
        </object>
 <object>
                <name>5h</name>
                <pose>Unspecified</pose>
                <truncated>0</truncated>
                <difficult>0</difficult>
                <bndbox>
                        <xmin>368</xmin>
                        <ymin>324</ymin>
                        <xmax>391</xmax>
                        <ymax>376</ymax>
                </bndbox>
        </object>
 <object>
                <name>5h</name>
                <pose>Unspecified</pose>
                <truncated>0</truncated>
                <difficult>0</difficult>
                <bndbox>
                        <xmin>502</xmin>
                        <ymin>485</ymin>
                        <xmax>524</xmax>
                        <ymax>536</ymax>
                </bndbox>
        </object>
</annotation>        
