<annotation>
        <folder>FOLDER</folder>
        <filename>061096054.jpg</filename>
        <path>data/scenes/val\061096054.jpg</path>
        <source>
                <database>Unknown</database>
        </source>
        <size>
                <width>720</width>
                <height>720</height>
                <depth>3</depth>
        </size>
 <object>
                <name>2c</name>
                <pose>Unspecified</pose>
                <truncated>0</truncated>
                <difficult>0</difficult>
                <bndbox>
                        <xmin>408</xmin>
                        <ymin>197</ymin>
                        <xmax>454</xmax>
                        <ymax>271</ymax>
                </bndbox>
        </object>
 <object>
                <name>2h</name>
                <pose>Unspecified</pose>
                <truncated>0</truncated>
                <difficult>0</difficult>
                <bndbox>
                        <xmin>454</xmin>
                        <ymin>214</ymin>
                        <xmax>499</xmax>
                        <ymax>288</ymax>
                </bndbox>
        </object>
 <object>
                <name>Jh</name>
                <pose>Unspecified</pose>
                <truncated>0</truncated>
                <difficult>0</difficult>
                <bndbox>
                        <xmin>520</xmin>
                        <ymin>278</ymin>
                        <xmax>583</xmax>
                        <ymax>339</ymax>
                </bndbox>
        </object>
 <object>
                <name>Jh</name>
                <pose>Unspecified</pose>
                <truncated>0</truncated>
                <difficult>0</difficult>
                <bndbox>
                        <xmin>504</xmin>
                        <ymin>599</ymin>
                        <xmax>566</xmax>
                        <ymax>659</ymax>
                </bndbox>
        </object>
</annotation>        
