<annotation>
        <folder>FOLDER</folder>
        <filename>075787785.jpg</filename>
        <path>data/scenes/val\075787785.jpg</path>
        <source>
                <database>Unknown</database>
        </source>
        <size>
                <width>720</width>
                <height>720</height>
                <depth>3</depth>
        </size>
 <object>
                <name>Jd</name>
                <pose>Unspecified</pose>
                <truncated>0</truncated>
                <difficult>0</difficult>
                <bndbox>
                        <xmin>139</xmin>
                        <ymin>507</ymin>
                        <xmax>213</xmax>
                        <ymax>546</ymax>
                </bndbox>
        </object>
 <object>
                <name>3s</name>
                <pose>Unspecified</pose>
                <truncated>0</truncated>
                <difficult>0</difficult>
                <bndbox>
                        <xmin>160</xmin>
                        <ymin>440</ymin>
                        <xmax>237</xmax>
                        <ymax>490</ymax>
                </bndbox>
        </object>
 <object>
                <name>Js</name>
                <pose>Unspecified</pose>
                <truncated>0</truncated>
                <difficult>0</difficult>
                <bndbox>
                        <xmin>225</xmin>
                        <ymin>354</ymin>
                        <xmax>289</xmax>
                        <ymax>418</ymax>
                </bndbox>
        </object>
 <object>
                <name>Js</name>
                <pose>Unspecified</pose>
                <truncated>0</truncated>
                <difficult>0</difficult>
                <bndbox>
                        <xmin>544</xmin>
                        <ymin>359</ymin>
                        <xmax>608</xmax>
                        <ymax>423</ymax>
                </bndbox>
        </object>
</annotation>        
