<annotation>
        <folder>FOLDER</folder>
        <filename>236865102.jpg</filename>
        <path>data/scenes/val\236865102.jpg</path>
        <source>
                <database>Unknown</database>
        </source>
        <size>
                <width>720</width>
                <height>720</height>
                <depth>3</depth>
        </size>
 <object>
                <name>Jh</name>
                <pose>Unspecified</pose>
                <truncated>0</truncated>
                <difficult>0</difficult>
                <bndbox>
                        <xmin>100</xmin>
                        <ymin>212</ymin>
                        <xmax>137</xmax>
                        <ymax>288</ymax>
                </bndbox>
        </object>
 <object>
                <name>7s</name>
                <pose>Unspecified</pose>
                <truncated>0</truncated>
                <difficult>0</difficult>
                <bndbox>
                        <xmin>161</xmin>
                        <ymin>202</ymin>
                        <xmax>200</xmax>
                        <ymax>281</ymax>
                </bndbox>
        </object>
 <object>
                <name>8d</name>
                <pose>Unspecified</pose>
                <truncated>0</truncated>
                <difficult>0</difficult>
                <bndbox>
                        <xmin>230</xmin>
                        <ymin>203</ymin>
                        <xmax>260</xmax>
                        <ymax>278</ymax>
                </bndbox>
        </object>
 <object>
                <name>8d</name>
                <pose>Unspecified</pose>
                <truncated>0</truncated>
                <difficult>0</difficult>
                <bndbox>
                        <xmin>434</xmin>
                        <ymin>449</ymin>
                        <xmax>464</xmax>
                        <ymax>523</ymax>
                </bndbox>
        </object>
</annotation>        
