<annotation>
        <folder>FOLDER</folder>
        <filename>301700143.jpg</filename>
        <path>data/scenes/val\301700143.jpg</path>
        <source>
                <database>Unknown</database>
        </source>
        <size>
                <width>720</width>
                <height>720</height>
                <depth>3</depth>
        </size>
 <object>
                <name>Js</name>
                <pose>Unspecified</pose>
                <truncated>0</truncated>
                <difficult>0</difficult>
                <bndbox>
                        <xmin>283</xmin>
                        <ymin>343</ymin>
                        <xmax>363</xmax>
                        <ymax>380</ymax>
                </bndbox>
        </object>
 <object>
                <name>Jd</name>
                <pose>Unspecified</pose>
                <truncated>0</truncated>
                <difficult>0</difficult>
                <bndbox>
                        <xmin>281</xmin>
                        <ymin>282</ymin>
                        <xmax>357</xmax>
                        <ymax>311</ymax>
                </bndbox>
        </object>
 <object>
                <name>7c</name>
                <pose>Unspecified</pose>
                <truncated>0</truncated>
                <difficult>0</difficult>
                <bndbox>
                        <xmin>291</xmin>
                        <ymin>206</ymin>
                        <xmax>368</xmax>
                        <ymax>246</ymax>
                </bndbox>
        </object>
 <object>
                <name>7c</name>
                <pose>Unspecified</pose>
                <truncated>0</truncated>
                <difficult>0</difficult>
                <bndbox>
                        <xmin>573</xmin>
                        <ymin>49</ymin>
                        <xmax>650</xmax>
                        <ymax>89</ymax>
                </bndbox>
        </object>
</annotation>        
