<annotation>
        <folder>FOLDER</folder>
        <filename>419874584.jpg</filename>
        <path>data/scenes/val\419874584.jpg</path>
        <source>
                <database>Unknown</database>
        </source>
        <size>
                <width>720</width>
                <height>720</height>
                <depth>3</depth>
        </size>
 <object>
                <name>Jc</name>
                <pose>Unspecified</pose>
                <truncated>0</truncated>
                <difficult>0</difficult>
                <bndbox>
                        <xmin>328</xmin>
                        <ymin>375</ymin>
                        <xmax>368</xmax>
                        <ymax>452</ymax>
                </bndbox>
        </object>
 <object>
                <name>8s</name>
                <pose>Unspecified</pose>
                <truncated>0</truncated>
                <difficult>0</difficult>
                <bndbox>
                        <xmin>258</xmin>
                        <ymin>382</ymin>
                        <xmax>289</xmax>
                        <ymax>461</ymax>
                </bndbox>
        </object>
 <object>
                <name>Kc</name>
                <pose>Unspecified</pose>
                <truncated>0</truncated>
                <difficult>0</difficult>
                <bndbox>
                        <xmin>203</xmin>
                        <ymin>375</ymin>
                        <xmax>241</xmax>
                        <ymax>455</ymax>
                </bndbox>
        </object>
 <object>
                <name>Kc</name>
                <pose>Unspecified</pose>
                <truncated>0</truncated>
                <difficult>0</difficult>
                <bndbox>
                        <xmin>15</xmin>
                        <ymin>122</ymin>
                        <xmax>49</xmax>
                        <ymax>197</ymax>
                </bndbox>
        </object>
</annotation>        
