<annotation>
        <folder>FOLDER</folder>
        <filename>450996149.jpg</filename>
        <path>data/scenes/val\450996149.jpg</path>
        <source>
                <database>Unknown</database>
        </source>
        <size>
                <width>720</width>
                <height>720</height>
                <depth>3</depth>
        </size>
 <object>
                <name>Jd</name>
                <pose>Unspecified</pose>
                <truncated>0</truncated>
                <difficult>0</difficult>
                <bndbox>
                        <xmin>526</xmin>
                        <ymin>374</ymin>
                        <xmax>573</xmax>
                        <ymax>408</ymax>
                </bndbox>
        </object>
 <object>
                <name>4s</name>
                <pose>Unspecified</pose>
                <truncated>0</truncated>
                <difficult>0</difficult>
                <bndbox>
                        <xmin>497</xmin>
                        <ymin>412</ymin>
                        <xmax>539</xmax>
                        <ymax>454</ymax>
                </bndbox>
        </object>
 <object>
                <name>Ac</name>
                <pose>Unspecified</pose>
                <truncated>0</truncated>
                <difficult>0</difficult>
                <bndbox>
                        <xmin>459</xmin>
                        <ymin>440</ymin>
                        <xmax>499</xmax>
                        <ymax>485</ymax>
                </bndbox>
        </object>
 <object>
                <name>Ac</name>
                <pose>Unspecified</pose>
                <truncated>0</truncated>
                <difficult>0</difficult>
                <bndbox>
                        <xmin>260</xmin>
                        <ymin>399</ymin>
                        <xmax>299</xmax>
                        <ymax>444</ymax>
                </bndbox>
        </object>
</annotation>        
