<annotation>
        <folder>FOLDER</folder>
        <filename>543108592.jpg</filename>
        <path>data/scenes/val\543108592.jpg</path>
        <source>
                <database>Unknown</database>
        </source>
        <size>
                <width>720</width>
                <height>720</height>
                <depth>3</depth>
        </size>
 <object>
                <name>9s</name>
                <pose>Unspecified</pose>
                <truncated>0</truncated>
                <difficult>0</difficult>
                <bndbox>
                        <xmin>31</xmin>
                        <ymin>463</ymin>
                        <xmax>105</xmax>
                        <ymax>514</ymax>
                </bndbox>
        </object>
 <object>
                <name>Qh</name>
                <pose>Unspecified</pose>
                <truncated>0</truncated>
                <difficult>0</difficult>
                <bndbox>
                        <xmin>82</xmin>
                        <ymin>406</ymin>
                        <xmax>156</xmax>
                        <ymax>464</ymax>
                </bndbox>
        </object>
 <object>
                <name>Jd</name>
                <pose>Unspecified</pose>
                <truncated>0</truncated>
                <difficult>0</difficult>
                <bndbox>
                        <xmin>153</xmin>
                        <ymin>350</ymin>
                        <xmax>202</xmax>
                        <ymax>420</ymax>
                </bndbox>
        </object>
 <object>
                <name>Jd</name>
                <pose>Unspecified</pose>
                <truncated>0</truncated>
                <difficult>0</difficult>
                <bndbox>
                        <xmin>464</xmin>
                        <ymin>439</ymin>
                        <xmax>512</xmax>
                        <ymax>508</ymax>
                </bndbox>
        </object>
</annotation>        
