<annotation>
        <folder>FOLDER</folder>
        <filename>586501295.jpg</filename>
        <path>data/scenes/val\586501295.jpg</path>
        <source>
                <database>Unknown</database>
        </source>
        <size>
                <width>720</width>
                <height>720</height>
                <depth>3</depth>
        </size>
 <object>
                <name>Qc</name>
                <pose>Unspecified</pose>
                <truncated>0</truncated>
                <difficult>0</difficult>
                <bndbox>
                        <xmin>348</xmin>
                        <ymin>274</ymin>
                        <xmax>397</xmax>
                        <ymax>311</ymax>
                </bndbox>
        </object>
 <object>
                <name>9c</name>
                <pose>Unspecified</pose>
                <truncated>0</truncated>
                <difficult>0</difficult>
                <bndbox>
                        <xmin>377</xmin>
                        <ymin>238</ymin>
                        <xmax>422</xmax>
                        <ymax>279</ymax>
                </bndbox>
        </object>
 <object>
                <name>10s</name>
                <pose>Unspecified</pose>
                <truncated>0</truncated>
                <difficult>0</difficult>
                <bndbox>
                        <xmin>405</xmin>
                        <ymin>211</ymin>
                        <xmax>445</xmax>
                        <ymax>257</ymax>
                </bndbox>
        </object>
 <object>
                <name>10s</name>
                <pose>Unspecified</pose>
                <truncated>0</truncated>
                <difficult>0</difficult>
                <bndbox>
                        <xmin>610</xmin>
                        <ymin>242</ymin>
                        <xmax>655</xmax>
                        <ymax>288</ymax>
                </bndbox>
        </object>
</annotation>        
