<annotation>
        <folder>FOLDER</folder>
        <filename>593398867.jpg</filename>
        <path>data/scenes/val\593398867.jpg</path>
        <source>
                <database>Unknown</database>
        </source>
        <size>
                <width>720</width>
                <height>720</height>
                <depth>3</depth>
        </size>
 <object>
                <name>Jc</name>
                <pose>Unspecified</pose>
                <truncated>0</truncated>
                <difficult>0</difficult>
                <bndbox>
                        <xmin>485</xmin>
                        <ymin>338</ymin>
                        <xmax>541</xmax>
                        <ymax>408</ymax>
                </bndbox>
        </object>
 <object>
                <name>6h</name>
                <pose>Unspecified</pose>
                <truncated>0</truncated>
                <difficult>0</difficult>
                <bndbox>
                        <xmin>444</xmin>
                        <ymin>364</ymin>
                        <xmax>495</xmax>
                        <ymax>435</ymax>
                </bndbox>
        </object>
 <object>
                <name>4d</name>
                <pose>Unspecified</pose>
                <truncated>0</truncated>
                <difficult>0</difficult>
                <bndbox>
                        <xmin>358</xmin>
                        <ymin>393</ymin>
                        <xmax>394</xmax>
                        <ymax>467</ymax>
                </bndbox>
        </object>
 <object>
                <name>4d</name>
                <pose>Unspecified</pose>
                <truncated>0</truncated>
                <difficult>0</difficult>
                <bndbox>
                        <xmin>100</xmin>
                        <ymin>205</ymin>
                        <xmax>135</xmax>
                        <ymax>279</ymax>
                </bndbox>
        </object>
</annotation>        
