<annotation>
        <folder>FOLDER</folder>
        <filename>595472437.jpg</filename>
        <path>data/scenes/val\595472437.jpg</path>
        <source>
                <database>Unknown</database>
        </source>
        <size>
                <width>720</width>
                <height>720</height>
                <depth>3</depth>
        </size>
 <object>
                <name>6s</name>
                <pose>Unspecified</pose>
                <truncated>0</truncated>
                <difficult>0</difficult>
                <bndbox>
                        <xmin>312</xmin>
                        <ymin>598</ymin>
                        <xmax>353</xmax>
                        <ymax>677</ymax>
                </bndbox>
        </object>
 <object>
                <name>4c</name>
                <pose>Unspecified</pose>
                <truncated>0</truncated>
                <difficult>0</difficult>
                <bndbox>
                        <xmin>251</xmin>
                        <ymin>578</ymin>
                        <xmax>302</xmax>
                        <ymax>648</ymax>
                </bndbox>
        </object>
 <object>
                <name>Ks</name>
                <pose>Unspecified</pose>
                <truncated>0</truncated>
                <difficult>0</difficult>
                <bndbox>
                        <xmin>173</xmin>
                        <ymin>528</ymin>
                        <xmax>237</xmax>
                        <ymax>600</ymax>
                </bndbox>
        </object>
 <object>
                <name>Ks</name>
                <pose>Unspecified</pose>
                <truncated>0</truncated>
                <difficult>0</difficult>
                <bndbox>
                        <xmin>173</xmin>
                        <ymin>204</ymin>
                        <xmax>238</xmax>
                        <ymax>275</ymax>
                </bndbox>
        </object>
</annotation>        
