<annotation>
        <folder>FOLDER</folder>
        <filename>638257392.jpg</filename>
        <path>data/scenes/val\638257392.jpg</path>
        <source>
                <database>Unknown</database>
        </source>
        <size>
                <width>720</width>
                <height>720</height>
                <depth>3</depth>
        </size>
 <object>
                <name>8s</name>
                <pose>Unspecified</pose>
                <truncated>0</truncated>
                <difficult>0</difficult>
                <bndbox>
                        <xmin>173</xmin>
                        <ymin>123</ymin>
                        <xmax>202</xmax>
                        <ymax>202</ymax>
                </bndbox>
        </object>
 <object>
                <name>9h</name>
                <pose>Unspecified</pose>
                <truncated>0</truncated>
                <difficult>0</difficult>
                <bndbox>
                        <xmin>229</xmin>
                        <ymin>136</ymin>
                        <xmax>266</xmax>
                        <ymax>213</ymax>
                </bndbox>
        </object>
 <object>
                <name>3s</name>
                <pose>Unspecified</pose>
                <truncated>0</truncated>
                <difficult>0</difficult>
                <bndbox>
                        <xmin>288</xmin>
                        <ymin>161</ymin>
                        <xmax>339</xmax>
                        <ymax>237</ymax>
                </bndbox>
        </object>
 <object>
                <name>3s</name>
                <pose>Unspecified</pose>
                <truncated>0</truncated>
                <difficult>0</difficult>
                <bndbox>
                        <xmin>374</xmin>
                        <ymin>471</ymin>
                        <xmax>424</xmax>
                        <ymax>550</ymax>
                </bndbox>
        </object>
</annotation>        
