<annotation>
        <folder>FOLDER</folder>
        <filename>646205492.jpg</filename>
        <path>data/scenes/val\646205492.jpg</path>
        <source>
                <database>Unknown</database>
        </source>
        <size>
                <width>720</width>
                <height>720</height>
                <depth>3</depth>
        </size>
 <object>
                <name>Kd</name>
                <pose>Unspecified</pose>
                <truncated>0</truncated>
                <difficult>0</difficult>
                <bndbox>
                        <xmin>191</xmin>
                        <ymin>225</ymin>
                        <xmax>237</xmax>
                        <ymax>302</ymax>
                </bndbox>
        </object>
 <object>
                <name>6c</name>
                <pose>Unspecified</pose>
                <truncated>0</truncated>
                <difficult>0</difficult>
                <bndbox>
                        <xmin>266</xmin>
                        <ymin>218</ymin>
                        <xmax>304</xmax>
                        <ymax>293</ymax>
                </bndbox>
        </object>
 <object>
                <name>7s</name>
                <pose>Unspecified</pose>
                <truncated>0</truncated>
                <difficult>0</difficult>
                <bndbox>
                        <xmin>355</xmin>
                        <ymin>224</ymin>
                        <xmax>390</xmax>
                        <ymax>304</ymax>
                </bndbox>
        </object>
 <object>
                <name>7s</name>
                <pose>Unspecified</pose>
                <truncated>0</truncated>
                <difficult>0</difficult>
                <bndbox>
                        <xmin>523</xmin>
                        <ymin>497</ymin>
                        <xmax>559</xmax>
                        <ymax>576</ymax>
                </bndbox>
        </object>
</annotation>        
