<annotation>
        <folder>FOLDER</folder>
        <filename>707291750.jpg</filename>
        <path>data/scenes/val\707291750.jpg</path>
        <source>
                <database>Unknown</database>
        </source>
        <size>
                <width>720</width>
                <height>720</height>
                <depth>3</depth>
        </size>
 <object>
                <name>9s</name>
                <pose>Unspecified</pose>
                <truncated>0</truncated>
                <difficult>0</difficult>
                <bndbox>
                        <xmin>71</xmin>
                        <ymin>393</ymin>
                        <xmax>150</xmax>
                        <ymax>421</ymax>
                </bndbox>
        </object>
 <object>
                <name>5d</name>
                <pose>Unspecified</pose>
                <truncated>0</truncated>
                <difficult>0</difficult>
                <bndbox>
                        <xmin>83</xmin>
                        <ymin>336</ymin>
                        <xmax>161</xmax>
                        <ymax>374</ymax>
                </bndbox>
        </object>
 <object>
                <name>5c</name>
                <pose>Unspecified</pose>
                <truncated>0</truncated>
                <difficult>0</difficult>
                <bndbox>
                        <xmin>116</xmin>
                        <ymin>255</ymin>
                        <xmax>191</xmax>
                        <ymax>308</ymax>
                </bndbox>
        </object>
 <object>
                <name>5c</name>
                <pose>Unspecified</pose>
                <truncated>0</truncated>
                <difficult>0</difficult>
                <bndbox>
                        <xmin>429</xmin>
                        <ymin>179</ymin>
                        <xmax>501</xmax>
                        <ymax>231</ymax>
                </bndbox>
        </object>
</annotation>        
