<annotation>
        <folder>FOLDER</folder>
        <filename>723936504.jpg</filename>
        <path>data/scenes/val\723936504.jpg</path>
        <source>
                <database>Unknown</database>
        </source>
        <size>
                <width>720</width>
                <height>720</height>
                <depth>3</depth>
        </size>
 <object>
                <name>2d</name>
                <pose>Unspecified</pose>
                <truncated>0</truncated>
                <difficult>0</difficult>
                <bndbox>
                        <xmin>391</xmin>
                        <ymin>585</ymin>
                        <xmax>432</xmax>
                        <ymax>627</ymax>
                </bndbox>
        </object>
 <object>
                <name>6h</name>
                <pose>Unspecified</pose>
                <truncated>0</truncated>
                <difficult>0</difficult>
                <bndbox>
                        <xmin>369</xmin>
                        <ymin>561</ymin>
                        <xmax>415</xmax>
                        <ymax>601</ymax>
                </bndbox>
        </object>
 <object>
                <name>Kc</name>
                <pose>Unspecified</pose>
                <truncated>0</truncated>
                <difficult>0</difficult>
                <bndbox>
                        <xmin>337</xmin>
                        <ymin>502</ymin>
                        <xmax>389</xmax>
                        <ymax>542</ymax>
                </bndbox>
        </object>
 <object>
                <name>Kc</name>
                <pose>Unspecified</pose>
                <truncated>0</truncated>
                <difficult>0</difficult>
                <bndbox>
                        <xmin>433</xmin>
                        <ymin>320</ymin>
                        <xmax>484</xmax>
                        <ymax>356</ymax>
                </bndbox>
        </object>
</annotation>        
