<annotation>
        <folder>FOLDER</folder>
        <filename>731636477.jpg</filename>
        <path>data/scenes/val\731636477.jpg</path>
        <source>
                <database>Unknown</database>
        </source>
        <size>
                <width>720</width>
                <height>720</height>
                <depth>3</depth>
        </size>
 <object>
                <name>2s</name>
                <pose>Unspecified</pose>
                <truncated>0</truncated>
                <difficult>0</difficult>
                <bndbox>
                        <xmin>314</xmin>
                        <ymin>483</ymin>
                        <xmax>360</xmax>
                        <ymax>524</ymax>
                </bndbox>
        </object>
 <object>
                <name>8h</name>
                <pose>Unspecified</pose>
                <truncated>0</truncated>
                <difficult>0</difficult>
                <bndbox>
                        <xmin>345</xmin>
                        <ymin>453</ymin>
                        <xmax>384</xmax>
                        <ymax>498</ymax>
                </bndbox>
        </object>
 <object>
                <name>7s</name>
                <pose>Unspecified</pose>
                <truncated>0</truncated>
                <difficult>0</difficult>
                <bndbox>
                        <xmin>392</xmin>
                        <ymin>426</ymin>
                        <xmax>429</xmax>
                        <ymax>478</ymax>
                </bndbox>
        </object>
 <object>
                <name>7s</name>
                <pose>Unspecified</pose>
                <truncated>0</truncated>
                <difficult>0</difficult>
                <bndbox>
                        <xmin>586</xmin>
                        <ymin>510</ymin>
                        <xmax>623</xmax>
                        <ymax>562</ymax>
                </bndbox>
        </object>
</annotation>        
