<annotation>
        <folder>FOLDER</folder>
        <filename>783864386.jpg</filename>
        <path>data/scenes/val\783864386.jpg</path>
        <source>
                <database>Unknown</database>
        </source>
        <size>
                <width>720</width>
                <height>720</height>
                <depth>3</depth>
        </size>
 <object>
                <name>Ks</name>
                <pose>Unspecified</pose>
                <truncated>0</truncated>
                <difficult>0</difficult>
                <bndbox>
                        <xmin>211</xmin>
                        <ymin>113</ymin>
                        <xmax>242</xmax>
                        <ymax>192</ymax>
                </bndbox>
        </object>
 <object>
                <name>Jd</name>
                <pose>Unspecified</pose>
                <truncated>0</truncated>
                <difficult>0</difficult>
                <bndbox>
                        <xmin>280</xmin>
                        <ymin>123</ymin>
                        <xmax>319</xmax>
                        <ymax>197</ymax>
                </bndbox>
        </object>
 <object>
                <name>9d</name>
                <pose>Unspecified</pose>
                <truncated>0</truncated>
                <difficult>0</difficult>
                <bndbox>
                        <xmin>352</xmin>
                        <ymin>154</ymin>
                        <xmax>399</xmax>
                        <ymax>226</ymax>
                </bndbox>
        </object>
 <object>
                <name>9d</name>
                <pose>Unspecified</pose>
                <truncated>0</truncated>
                <difficult>0</difficult>
                <bndbox>
                        <xmin>440</xmin>
                        <ymin>464</ymin>
                        <xmax>485</xmax>
                        <ymax>535</ymax>
                </bndbox>
        </object>
</annotation>        
