<annotation>
        <folder>FOLDER</folder>
        <filename>834636588.jpg</filename>
        <path>data/scenes/val\834636588.jpg</path>
        <source>
                <database>Unknown</database>
        </source>
        <size>
                <width>720</width>
                <height>720</height>
                <depth>3</depth>
        </size>
 <object>
                <name>10c</name>
                <pose>Unspecified</pose>
                <truncated>0</truncated>
                <difficult>0</difficult>
                <bndbox>
                        <xmin>362</xmin>
                        <ymin>199</ymin>
                        <xmax>438</xmax>
                        <ymax>233</ymax>
                </bndbox>
        </object>
 <object>
                <name>6c</name>
                <pose>Unspecified</pose>
                <truncated>0</truncated>
                <difficult>0</difficult>
                <bndbox>
                        <xmin>361</xmin>
                        <ymin>255</ymin>
                        <xmax>437</xmax>
                        <ymax>288</ymax>
                </bndbox>
        </object>
 <object>
                <name>10s</name>
                <pose>Unspecified</pose>
                <truncated>0</truncated>
                <difficult>0</difficult>
                <bndbox>
                        <xmin>349</xmin>
                        <ymin>316</ymin>
                        <xmax>427</xmax>
                        <ymax>356</ymax>
                </bndbox>
        </object>
 <object>
                <name>10s</name>
                <pose>Unspecified</pose>
                <truncated>0</truncated>
                <difficult>0</difficult>
                <bndbox>
                        <xmin>64</xmin>
                        <ymin>461</ymin>
                        <xmax>143</xmax>
                        <ymax>500</ymax>
                </bndbox>
        </object>
</annotation>        
