<annotation>
        <folder>FOLDER</folder>
        <filename>865702669.jpg</filename>
        <path>data/scenes/val\865702669.jpg</path>
        <source>
                <database>Unknown</database>
        </source>
        <size>
                <width>720</width>
                <height>720</height>
                <depth>3</depth>
        </size>
 <object>
                <name>Jd</name>
                <pose>Unspecified</pose>
                <truncated>0</truncated>
                <difficult>0</difficult>
                <bndbox>
                        <xmin>222</xmin>
                        <ymin>397</ymin>
                        <xmax>269</xmax>
                        <ymax>431</ymax>
                </bndbox>
        </object>
 <object>
                <name>4h</name>
                <pose>Unspecified</pose>
                <truncated>0</truncated>
                <difficult>0</difficult>
                <bndbox>
                        <xmin>202</xmin>
                        <ymin>356</ymin>
                        <xmax>253</xmax>
                        <ymax>383</ymax>
                </bndbox>
        </object>
 <object>
                <name>Qs</name>
                <pose>Unspecified</pose>
                <truncated>0</truncated>
                <difficult>0</difficult>
                <bndbox>
                        <xmin>192</xmin>
                        <ymin>315</ymin>
                        <xmax>245</xmax>
                        <ymax>342</ymax>
                </bndbox>
        </object>
 <object>
                <name>Qs</name>
                <pose>Unspecified</pose>
                <truncated>0</truncated>
                <difficult>0</difficult>
                <bndbox>
                        <xmin>319</xmin>
                        <ymin>151</ymin>
                        <xmax>371</xmax>
                        <ymax>177</ymax>
                </bndbox>
        </object>
</annotation>        
