<annotation>
        <folder>FOLDER</folder>
        <filename>885439522.jpg</filename>
        <path>data/scenes/val\885439522.jpg</path>
        <source>
                <database>Unknown</database>
        </source>
        <size>
                <width>720</width>
                <height>720</height>
                <depth>3</depth>
        </size>
 <object>
                <name>4s</name>
                <pose>Unspecified</pose>
                <truncated>0</truncated>
                <difficult>0</difficult>
                <bndbox>
                        <xmin>460</xmin>
                        <ymin>327</ymin>
                        <xmax>498</xmax>
                        <ymax>374</ymax>
                </bndbox>
        </object>
 <object>
                <name>Jc</name>
                <pose>Unspecified</pose>
                <truncated>0</truncated>
                <difficult>0</difficult>
                <bndbox>
                        <xmin>434</xmin>
                        <ymin>309</ymin>
                        <xmax>477</xmax>
                        <ymax>353</ymax>
                </bndbox>
        </object>
 <object>
                <name>10c</name>
                <pose>Unspecified</pose>
                <truncated>0</truncated>
                <difficult>0</difficult>
                <bndbox>
                        <xmin>394</xmin>
                        <ymin>261</ymin>
                        <xmax>441</xmax>
                        <ymax>298</ymax>
                </bndbox>
        </object>
 <object>
                <name>10c</name>
                <pose>Unspecified</pose>
                <truncated>0</truncated>
                <difficult>0</difficult>
                <bndbox>
                        <xmin>453</xmin>
                        <ymin>62</ymin>
                        <xmax>500</xmax>
                        <ymax>103</ymax>
                </bndbox>
        </object>
</annotation>        
