<annotation>
        <folder>FOLDER</folder>
        <filename>894289862.jpg</filename>
        <path>data/scenes/val\894289862.jpg</path>
        <source>
                <database>Unknown</database>
        </source>
        <size>
                <width>720</width>
                <height>720</height>
                <depth>3</depth>
        </size>
 <object>
                <name>5d</name>
                <pose>Unspecified</pose>
                <truncated>0</truncated>
                <difficult>0</difficult>
                <bndbox>
                        <xmin>521</xmin>
                        <ymin>304</ymin>
                        <xmax>588</xmax>
                        <ymax>365</ymax>
                </bndbox>
        </object>
 <object>
                <name>10c</name>
                <pose>Unspecified</pose>
                <truncated>0</truncated>
                <difficult>0</difficult>
                <bndbox>
                        <xmin>460</xmin>
                        <ymin>349</ymin>
                        <xmax>514</xmax>
                        <ymax>419</ymax>
                </bndbox>
        </object>
 <object>
                <name>2c</name>
                <pose>Unspecified</pose>
                <truncated>0</truncated>
                <difficult>0</difficult>
                <bndbox>
                        <xmin>385</xmin>
                        <ymin>380</ymin>
                        <xmax>433</xmax>
                        <ymax>455</ymax>
                </bndbox>
        </object>
 <object>
                <name>2c</name>
                <pose>Unspecified</pose>
                <truncated>0</truncated>
                <difficult>0</difficult>
                <bndbox>
                        <xmin>109</xmin>
                        <ymin>221</ymin>
                        <xmax>154</xmax>
                        <ymax>294</ymax>
                </bndbox>
        </object>
</annotation>        
