<annotation>
        <folder>FOLDER</folder>
        <filename>898005823.jpg</filename>
        <path>data/scenes/val\898005823.jpg</path>
        <source>
                <database>Unknown</database>
        </source>
        <size>
                <width>720</width>
                <height>720</height>
                <depth>3</depth>
        </size>
 <object>
                <name>Ac</name>
                <pose>Unspecified</pose>
                <truncated>0</truncated>
                <difficult>0</difficult>
                <bndbox>
                        <xmin>401</xmin>
                        <ymin>285</ymin>
                        <xmax>453</xmax>
                        <ymax>309</ymax>
                </bndbox>
        </object>
 <object>
                <name>6h</name>
                <pose>Unspecified</pose>
                <truncated>0</truncated>
                <difficult>0</difficult>
                <bndbox>
                        <xmin>391</xmin>
                        <ymin>328</ymin>
                        <xmax>443</xmax>
                        <ymax>356</ymax>
                </bndbox>
        </object>
 <object>
                <name>2h</name>
                <pose>Unspecified</pose>
                <truncated>0</truncated>
                <difficult>0</difficult>
                <bndbox>
                        <xmin>383</xmin>
                        <ymin>359</ymin>
                        <xmax>434</xmax>
                        <ymax>388</ymax>
                </bndbox>
        </object>
 <object>
                <name>2h</name>
                <pose>Unspecified</pose>
                <truncated>0</truncated>
                <difficult>0</difficult>
                <bndbox>
                        <xmin>188</xmin>
                        <ymin>431</ymin>
                        <xmax>238</xmax>
                        <ymax>461</ymax>
                </bndbox>
        </object>
</annotation>        
