<annotation>
        <folder>FOLDER</folder>
        <filename>956793373.jpg</filename>
        <path>data/scenes/val\956793373.jpg</path>
        <source>
                <database>Unknown</database>
        </source>
        <size>
                <width>720</width>
                <height>720</height>
                <depth>3</depth>
        </size>
 <object>
                <name>Ks</name>
                <pose>Unspecified</pose>
                <truncated>0</truncated>
                <difficult>0</difficult>
                <bndbox>
                        <xmin>177</xmin>
                        <ymin>307</ymin>
                        <xmax>216</xmax>
                        <ymax>387</ymax>
                </bndbox>
        </object>
 <object>
                <name>Ac</name>
                <pose>Unspecified</pose>
                <truncated>0</truncated>
                <difficult>0</difficult>
                <bndbox>
                        <xmin>250</xmin>
                        <ymin>308</ymin>
                        <xmax>284</xmax>
                        <ymax>385</ymax>
                </bndbox>
        </object>
 <object>
                <name>2h</name>
                <pose>Unspecified</pose>
                <truncated>0</truncated>
                <difficult>0</difficult>
                <bndbox>
                        <xmin>329</xmin>
                        <ymin>327</ymin>
                        <xmax>370</xmax>
                        <ymax>403</ymax>
                </bndbox>
        </object>
 <object>
                <name>2h</name>
                <pose>Unspecified</pose>
                <truncated>0</truncated>
                <difficult>0</difficult>
                <bndbox>
                        <xmin>445</xmin>
                        <ymin>628</ymin>
                        <xmax>487</xmax>
                        <ymax>703</ymax>
                </bndbox>
        </object>
</annotation>        
