<annotation>
        <folder>FOLDER</folder>
        <filename>976736840.jpg</filename>
        <path>data/scenes/val\976736840.jpg</path>
        <source>
                <database>Unknown</database>
        </source>
        <size>
                <width>720</width>
                <height>720</height>
                <depth>3</depth>
        </size>
 <object>
                <name>Qd</name>
                <pose>Unspecified</pose>
                <truncated>0</truncated>
                <difficult>0</difficult>
                <bndbox>
                        <xmin>228</xmin>
                        <ymin>189</ymin>
                        <xmax>272</xmax>
                        <ymax>227</ymax>
                </bndbox>
        </object>
 <object>
                <name>5h</name>
                <pose>Unspecified</pose>
                <truncated>0</truncated>
                <difficult>0</difficult>
                <bndbox>
                        <xmin>248</xmin>
                        <ymin>237</ymin>
                        <xmax>298</xmax>
                        <ymax>269</ymax>
                </bndbox>
        </object>
 <object>
                <name>Qh</name>
                <pose>Unspecified</pose>
                <truncated>0</truncated>
                <difficult>0</difficult>
                <bndbox>
                        <xmin>257</xmin>
                        <ymin>297</ymin>
                        <xmax>310</xmax>
                        <ymax>325</ymax>
                </bndbox>
        </object>
 <object>
                <name>Qh</name>
                <pose>Unspecified</pose>
                <truncated>0</truncated>
                <difficult>0</difficult>
                <bndbox>
                        <xmin>120</xmin>
                        <ymin>455</ymin>
                        <xmax>172</xmax>
                        <ymax>479</ymax>
                </bndbox>
        </object>
</annotation>        
